LICENSE
MANIFEST.in
README.md
requirements.txt
setup.py
pynwm/__init__.py
pynwm/data_service.py
pynwm.egg-info/PKG-INFO
pynwm.egg-info/SOURCES.txt
pynwm.egg-info/dependency_links.txt
pynwm.egg-info/requires.txt
pynwm.egg-info/top_level.txt
pynwm/data/long_range.json
pynwm/data/medium_range.json
pynwm/data/short_range.json