Metadata-Version: 2.1
Name: pynwm
Version: 0.1.1
Summary: Tools for getting data from the United States National Water Model
Home-page: UNKNOWN
Author: Riley Hales
License: BSD 3-Clause Clear
Platform: UNKNOWN
Classifier: Programming Language :: Python :: 3
Classifier: Topic :: Scientific/Engineering :: Information Analysis
Classifier: Intended Audience :: Science/Research
Classifier: License :: OSI Approved :: BSD License
Classifier: Natural Language :: English
Classifier: Operating System :: OS Independent
Requires-Python: >=3
